src/btcturk_api/__init__.py
src/btcturk_api/client.py
src/btcturk_api/constants.py
src/btcturk_api/exceptions.py
src/btcturk_api/properties.py
btcturk_api_wrapper-0.1.0.dist-info/LICENSE.txt
btcturk_api_wrapper-0.1.0.dist-info/METADATA
btcturk_api_wrapper-0.1.0.dist-info/WHEEL
btcturk_api_wrapper-0.1.0.dist-info/top_level.txt
btcturk_api_wrapper-0.1.0.dist-info/RECORD
